coupled_biased_random_walks/__init__.py
coupled_biased_random_walks/_version.py
coupled_biased_random_walks/count.py
coupled_biased_random_walks/detect.py
coupled_biased_random_walks/matrix.py
coupled_biased_random_walks/types.py
coupled_biased_random_walks-2.1.1.dist-info/LICENSE
coupled_biased_random_walks-2.1.1.dist-info/METADATA
coupled_biased_random_walks-2.1.1.dist-info/WHEEL
coupled_biased_random_walks-2.1.1.dist-info/top_level.txt
coupled_biased_random_walks-2.1.1.dist-info/RECORD
