Metadata-Version: 2.1
Name: coupled_biased_random_walks
Version: 2.1.1
Summary: Outlier detection for categorical data
Home-page: https://github.com/dkaslovsky/Coupled-Biased-Random-Walks
Author: Daniel Kaslovsky
Author-email: dkaslovsky@gmail.com
License: MIT
Keywords: anomaly detection, outlier detection,categorical data,random walk
Classifier: Environment :: Console
Classifier: License :: OSI Approved :: MIT License
Classifier: Natural Language :: English
Classifier: Operating System :: OS Independent
Classifier: Programming Language :: Python :: 3.12
License-File: LICENSE
Requires-Dist: numpy ==2.0.0
Requires-Dist: scipy ==1.14.0
Requires-Dist: setuptools ==70.3.0
